{
  "objectInfo" : {
    "id" : "6LYVQNoT9wukUQpg3BUb0g",
    "name" : "FileList - SFTP",
    "type" : "MI_TASK",
    "metadata" : {
      "modelVersion" : {
        "major" : 1,
        "minor" : 0
      },
      "repoInfo" : {
        "repoHandle" : "114274"
      },
      "contextAttributes" : [ ],
      "additionalInfo" : {
        "description" : "",
        "contentType" : null,
        "documentState" : "VALID"
      }
    }
  },
  "dataFileExtension" : "dat",
  "updateTime" : "2025-05-28T15:08:37.585Z",
  "objectRefs" : [ {
    "id" : "aalqzHRpNEqkTrsSWJlMSL",
    "name" : "AParentOrg",
    "type" : "AgentGroup",
    "metadata" : {
      "modelVersion" : {
        "major" : 0,
        "minor" : 0
      },
      "repoInfo" : {
        "repoHandle" : "01001D25000000000002"
      },
      "contextAttributes" : null,
      "additionalInfo" : {
        "description" : null,
        "contentType" : "JSON",
        "documentState" : "VALID"
      }
    },
    "path" : "/SYS"
  }, {
    "id" : "1TO5AKP1AQ1i65I1fowF8x",
    "name" : "autosftp",
    "type" : "Connection",
    "metadata" : {
      "modelVersion" : {
        "major" : 0,
        "minor" : 0
      },
      "repoInfo" : {
        "repoHandle" : "01001D0B000000000JUC"
      },
      "contextAttributes" : null,
      "additionalInfo" : {
        "description" : "autoSFTP_AParentOrg_desc",
        "contentType" : "JSON",
        "documentState" : "COMPLETE"
      }
    },
    "path" : "/SYS"
  } ],
  "readableFileExtension" : "json",
  "readableFilePresent" : true
}